{
  "n_postings": 1404,
  "n_features": 29,
  "n_test": 281,
  "baseline_mae": 43148,
  "mae": 36360,
  "r2": 0.221,
  "mae_improvement_pct": 15.7,
  "premiums": [
    {
      "skill": "Machine Learning",
      "delta": 22748
    },
    {
      "skill": "ETL",
      "delta": 18821
    },
    {
      "skill": "Experimentation",
      "delta": 13810
    },
    {
      "skill": "AWS",
      "delta": 12117
    },
    {
      "skill": "Statistics",
      "delta": 10610
    },
    {
      "skill": "Generative AI",
      "delta": 6977
    },
    {
      "skill": "Azure",
      "delta": -211
    },
    {
      "skill": "Data Modeling",
      "delta": -1222
    },
    {
      "skill": "Spark",
      "delta": -2314
    },
    {
      "skill": "Snowflake",
      "delta": -2518
    },
    {
      "skill": "Databricks",
      "delta": -11882
    },
    {
      "skill": "Data Governance",
      "delta": -12777
    },
    {
      "skill": "SQL",
      "delta": -15385
    },
    {
      "skill": "Computer Vision",
      "delta": -15402
    }
  ]
}